COPYING
setup.py
bin/brz-build-daily-recipe
bin/brz-build-recipe
brz_builder.egg-info/PKG-INFO
brz_builder.egg-info/SOURCES.txt
brz_builder.egg-info/dependency_links.txt
brz_builder.egg-info/requires.txt
brz_builder.egg-info/top_level.txt
brzbuildrecipe/__init__.py
brzbuildrecipe/build.py
brzbuildrecipe/dailydeb.py
brzbuildrecipe/deb_util.py
brzbuildrecipe/deb_version.py
brzbuildrecipe/main.py
brzbuildrecipe/ppa.py
brzbuildrecipe/recipe.py
brzbuildrecipe/tests/__init__.py
brzbuildrecipe/tests/test_blackbox.py
brzbuildrecipe/tests/test_deb_version.py
brzbuildrecipe/tests/test_recipe.py